odc_client.py
odc_client-0.2.3.dist-info/entry_points.txt
odc_client-0.2.3.dist-info/LICENSE
odc_client-0.2.3.dist-info/WHEEL
odc_client-0.2.3.dist-info/METADATA
odc_client-0.2.3.dist-info/RECORD
