Metadata-Version: 2.1
Name: odc-client
Version: 0.2.3
Summary: A small CLI tool to help with working with the ODC Server.
Author-email: Sjors Smits <smits.sjors@gmail.com>
Requires-Python: >=3.6
Classifier: License :: OSI Approved :: MIT License
Requires-Dist: typer[all] >=0.7
Requires-Dist: fabric >=3.0
Project-URL: Source, https://github.com/smitssjors/odc-client
